transsnet_afnews_common/__init__.py
transsnet_afnews_common/utils/__init__.py
transsnet_afnews_common-1.0.1.dev5.dist-info/METADATA
transsnet_afnews_common-1.0.1.dev5.dist-info/WHEEL
transsnet_afnews_common-1.0.1.dev5.dist-info/top_level.txt
transsnet_afnews_common-1.0.1.dev5.dist-info/RECORD
