Metadata-Version: 2.1
Name: transsnet-afnews-common
Version: 1.0.1.dev5
Summary: python common utils for transsnet africa news
Home-page: https://git.ms.netease.com/africaNews/python-common
Author: UNKNOWN
Author-email: UNKNOWN
License: UNKNOWN
Platform: UNKNOWN
Requires-Dist: redis
Requires-Dist: redis-py-cluster
